bus_ride/__init__.py
bus_ride/command.py
bus_ride/event.py
bus_ride/exceptions.py
bus_ride/handler.py
bus_ride/messagebus.py
bus_ride/receiver.py
bus_ride/returnmessage.py
bus_ride-0.1.0.dist-info/METADATA
bus_ride-0.1.0.dist-info/WHEEL
bus_ride-0.1.0.dist-info/licenses/AUTHORS.rst
bus_ride-0.1.0.dist-info/licenses/LICENSE
bus_ride-0.1.0.dist-info/RECORD
