Metadata-Version: 2.4
Name: bus_ride
Version: 0.1.0
Summary: A simple Message Bus implementation, based on Architecture Patterns With Python.
Project-URL: Repository, https://github.com/eyesee1/bus_ride
Author-email: "Duna C." <marinas.bobble-05@icloud.com>
Maintainer-email: "Duna C." <marinas.bobble-05@icloud.com>
License-Expression: MIT
License-File: AUTHORS.rst
License-File: LICENSE
Classifier: Development Status :: 4 - Beta
Classifier: Intended Audience :: Developers
Classifier: License :: OSI Approved :: MIT License
Classifier: Natural Language :: English
Classifier: Programming Language :: Python :: 3
Classifier: Programming Language :: Python :: 3.12
Classifier: Topic :: Software Development :: Libraries
Requires-Python: >=3.12
Requires-Dist: attrs>=24.3.0
